netbox_powerdns_sync/__init__.py
netbox_powerdns_sync/api/__init__.py
netbox_powerdns_sync/api/nested_serializers.py
netbox_powerdns_sync/api/serializers.py
netbox_powerdns_sync/api/urls.py
netbox_powerdns_sync/api/views.py
netbox_powerdns_sync/choices.py
netbox_powerdns_sync/constants.py
netbox_powerdns_sync/exceptions.py
netbox_powerdns_sync/fields.py
netbox_powerdns_sync/filtersets.py
netbox_powerdns_sync/forms/__init__.py
netbox_powerdns_sync/forms/filtersets.py
netbox_powerdns_sync/forms/model_forms.py
netbox_powerdns_sync/forms/sync.py
netbox_powerdns_sync/jobs.py
netbox_powerdns_sync/migrations/0001_initial.py
netbox_powerdns_sync/migrations/__init__.py
netbox_powerdns_sync/models.py
netbox_powerdns_sync/naming.py
netbox_powerdns_sync/navigation.py
netbox_powerdns_sync/querysets.py
netbox_powerdns_sync/record.py
netbox_powerdns_sync/signals.py
netbox_powerdns_sync/tables.py
netbox_powerdns_sync/templates/netbox_powerdns_sync/apiserver.html
netbox_powerdns_sync/templates/netbox_powerdns_sync/htmx/sync_result.html
netbox_powerdns_sync/templates/netbox_powerdns_sync/sync_result.html
netbox_powerdns_sync/templates/netbox_powerdns_sync/sync_schedule.html
netbox_powerdns_sync/templates/netbox_powerdns_sync/syncs.html
netbox_powerdns_sync/templates/netbox_powerdns_sync/zone.html
netbox_powerdns_sync/urls.py
netbox_powerdns_sync/utils.py
netbox_powerdns_sync/validators.py
netbox_powerdns_sync/version.py
netbox_powerdns_sync/views/__init__.py
netbox_powerdns_sync/views/api_servers.py
netbox_powerdns_sync/views/syncs.py
netbox_powerdns_sync/views/zones.py
netbox_powerdns_sync-0.0.8.dist-info/LICENSE
netbox_powerdns_sync-0.0.8.dist-info/METADATA
netbox_powerdns_sync-0.0.8.dist-info/WHEEL
netbox_powerdns_sync-0.0.8.dist-info/RECORD
