Metadata-Version: 2.1
Name: netbox-powerdns-sync
Version: 0.0.8
Summary: Sync DNS records in PowerDNS with NetBox
Home-page: https://github.com/ArnesSI/netbox-powerdns-sync/
License: MIT
Keywords: netbox,netbox-plugin,powerdns
Author: Matej Vadnjal
Author-email: matej.vadnjal@arnes.si
Requires-Python: >=3.9
Classifier: License :: OSI Approved :: MIT License
Classifier: Programming Language :: Python :: 3
Classifier: Programming Language :: Python :: 3.9
Classifier: Programming Language :: Python :: 3.10
Classifier: Programming Language :: Python :: 3.11
Requires-Dist: python-powerdns (>=2.1.0,<3.0.0)
